flytekitplugins_openai-1.16.12-py3.14-nspkg.pth
flytekitplugins/openai/__init__.py
flytekitplugins/openai/batch/__init__.py
flytekitplugins/openai/batch/connector.py
flytekitplugins/openai/batch/task.py
flytekitplugins/openai/batch/workflow.py
flytekitplugins/openai/chatgpt/__init__.py
flytekitplugins/openai/chatgpt/connector.py
flytekitplugins/openai/chatgpt/task.py
flytekitplugins_openai-1.16.12.dist-info/METADATA
flytekitplugins_openai-1.16.12.dist-info/WHEEL
flytekitplugins_openai-1.16.12.dist-info/entry_points.txt
flytekitplugins_openai-1.16.12.dist-info/namespace_packages.txt
flytekitplugins_openai-1.16.12.dist-info/top_level.txt
flytekitplugins_openai-1.16.12.dist-info/RECORD
